pyngrok/__init__.py
pyngrok/agent.py
pyngrok/conf.py
pyngrok/exception.py
pyngrok/installer.py
pyngrok/log.py
pyngrok/ngrok.py
pyngrok/process.py
pyngrok-7.2.13.dist-info/licenses/LICENSE
pyngrok-7.2.13.dist-info/METADATA
pyngrok-7.2.13.dist-info/WHEEL
pyngrok-7.2.13.dist-info/entry_points.txt
pyngrok-7.2.13.dist-info/top_level.txt
pyngrok-7.2.13.dist-info/RECORD
