Metadata-Version: 2.4
Name: pyngrok
Version: 7.2.13
Summary: A Python wrapper for ngrok
Author-email: Alex Laird <contact@alexlaird.com>
Maintainer-email: Alex Laird <contact@alexlaird.com>
License-Expression: MIT
Project-URL: Changelog, https://github.com/alexdlaird/pyngrok/blob/main/CHANGELOG.md
Project-URL: Documentation, https://pyngrok.readthedocs.io
Project-URL: Sponsor, https://github.com/sponsors/alexdlaird
Project-URL: Source Code, https://github.com/alexdlaird/pyngrok
Keywords: tunnel,webhook,reverse-proxy,ngrok,localhost,ingress,tunneling
Classifier: Development Status :: 6 - Mature
Classifier: Environment :: Console
Classifier: Environment :: Web Environment
Classifier: Intended Audience :: Developers
Classifier: Operating System :: MacOS
Classifier: Operating System :: Microsoft :: Windows
Classifier: Operating System :: OS Independent
Classifier: Operating System :: POSIX
Classifier: Operating System :: POSIX :: BSD :: FreeBSD
Classifier: Operating System :: POSIX :: Linux
Classifier: Operating System :: Unix
Classifier: Programming Language :: Python :: 3
Classifier: Programming Language :: Python :: 3.9
Classifier: Programming Language :: Python :: 3.10
Classifier: Programming Language :: Python :: 3.11
Classifier: Programming Language :: Python :: 3.12
Classifier: Programming Language :: Python :: 3.13
Classifier: Programming Language :: Python :: Implementation :: CPython
Classifier: Programming Language :: Python :: Implementation :: PyPy
Classifier: Topic :: Database :: Database Engines/Servers
Classifier: Topic :: Internet :: Proxy Servers
Classifier: Topic :: Internet :: WWW/HTTP :: Dynamic Content
Classifier: Topic :: Internet :: WWW/HTTP :: HTTP Servers
Classifier: Topic :: Software Development :: Build Tools
Classifier: Topic :: Software Development :: Testing
Classifier: Topic :: Software Development :: Libraries :: Python Modules
Requires-Python: >=3.9
License-File: LICENSE
Requires-Dist: PyYAML>=5.1
Provides-Extra: dev
Requires-Dist: pytest; extra == "dev"
Requires-Dist: coverage[toml]; extra == "dev"
Requires-Dist: psutil; extra == "dev"
Requires-Dist: flake8; extra == "dev"
Requires-Dist: flake8-pyproject; extra == "dev"
Requires-Dist: pep8-naming; extra == "dev"
Provides-Extra: docs
Requires-Dist: Sphinx<8.2; extra == "docs"
Requires-Dist: sphinx-notfound-page; extra == "docs"
Requires-Dist: sphinx_autodoc_typehints==1.25.2; extra == "docs"
Requires-Dist: sphinx-substitution-extensions; extra == "docs"
Requires-Dist: mypy; extra == "docs"
Requires-Dist: types-PyYAML; extra == "docs"
Dynamic: license-file
